{"trial_id": "0064", "hyperparameters": {"space": [{"class_name": "Int", "config": {"name": "units", "default": null, "conditions": [], "min_value": 32, "max_value": 128, "step": 32, "sampling": "linear"}}, {"class_name": "Float", "config": {"name": "dropout_rate", "default": 0.0, "conditions": [], "min_value": 0.0, "max_value": 0.5, "step": 0.1, "sampling": "linear"}}, {"class_name": "Boolean", "config": {"name": "second_layer", "default": false, "conditions": []}}, {"class_name": "Float", "config": {"name": "learning_rate", "default": 0.0001, "conditions": [], "min_value": 0.0001, "max_value": 0.01, "step": null, "sampling": "log"}}, {"class_name": "Int", "config": {"name": "units2", "default": null, "conditions": [], "min_value": 32, "max_value": 128, "step": 32, "sampling": "linear"}}], "values": {"units": 32, "dropout_rate": 0.2, "second_layer": false, "learning_rate": 0.002841876631465565, "units2": 96, "tuner/epochs": 4, "tuner/initial_epoch": 0, "tuner/bracket": 2, "tuner/round": 0}}, "metrics": {"metrics": {"loss": {"direction": "min", "observations": [{"value": [0.00012632922152988613], "step": 3}]}, "mae": {"direction": "min", "observations": [{"value": [0.007661580108106136], "step": 3}]}, "mape": {"direction": "min", "observations": [{"value": [15.605243682861328], "step": 3}]}, "val_loss": {"direction": "min", "observations": [{"value": [0.003216173266991973], "step": 3}]}, "val_mae": {"direction": "min", "observations": [{"value": [0.039338331669569016], "step": 3}]}, "val_mape": {"direction": "min", "observations": [{"value": [5.4674458503723145], "step": 3}]}}}, "score": 0.003216173266991973, "best_step": 3, "status": "COMPLETED", "message": null}